odoo9_addon_l10n_nl_bsn-9.0.1.0.0-py3.8-nspkg.pth
odoo_addons/l10n_nl_bsn/README.rst
odoo_addons/l10n_nl_bsn/__init__.py
odoo_addons/l10n_nl_bsn/__openerp__.py
odoo_addons/l10n_nl_bsn/i18n/l10n_nl_bsn.pot
odoo_addons/l10n_nl_bsn/i18n/nl.po
odoo_addons/l10n_nl_bsn/models/__init__.py
odoo_addons/l10n_nl_bsn/models/res_partner.py
odoo_addons/l10n_nl_bsn/static/description/icon.png
odoo_addons/l10n_nl_bsn/views/res_partner.xml
odoo9_addon_l10n_nl_bsn-9.0.1.0.0.dist-info/METADATA
odoo9_addon_l10n_nl_bsn-9.0.1.0.0.dist-info/WHEEL
odoo9_addon_l10n_nl_bsn-9.0.1.0.0.dist-info/namespace_packages.txt
odoo9_addon_l10n_nl_bsn-9.0.1.0.0.dist-info/top_level.txt
odoo9_addon_l10n_nl_bsn-9.0.1.0.0.dist-info/RECORD
